fastrpi/__init__.py
fastrpi/checks.py
fastrpi/config.py
fastrpi/exceptions.py
fastrpi/helpers.py
fastrpi/manifest.py
fastrpi/manifest_schemas.py
fastrpi/package.py
fastrpi/packageinfo.py
fastrpi/record.py
fastrpi/repository.py
fastrpi/repositorybackend.py
fastrpi/cli/__init__.py
fastrpi/cli/create.py
fastrpi/cli/describe.py
fastrpi/cli/edit.py
fastrpi/cli/init.py
fastrpi/cli/install.py
fastrpi/cli/list.py
fastrpi/cli/publish.py
fastrpi/cli/run.py
fastrpi/create/__init__.py
fastrpi/create/extract.py
fastrpi/create/packagecreator.py
fastrpi/server/__init__.py
fastrpi/server/metadatacollector.py
fastrpi/server/utils.py
tests/__init__.py
tests/conftest.py
tests/test_checks.py
tests/test_cli.py
tests/test_config.py
tests/test_dockerrepositorybackend.py
tests/test_gitrepositorybackend.py
tests/test_installrecord.py
tests/test_manifest.py
tests/test_package.py
tests/test_packageinfo.py
tests/test_packagerepository.py
fastrpi-1.0.1.dist-info/LICENSE
fastrpi-1.0.1.dist-info/METADATA
fastrpi-1.0.1.dist-info/WHEEL
fastrpi-1.0.1.dist-info/entry_points.txt
fastrpi-1.0.1.dist-info/top_level.txt
fastrpi-1.0.1.dist-info/RECORD
