Metadata-Version: 2.1
Name: fastrpi
Version: 1.0.1
Summary: FastrPI is a client to interact with a FastrPI repository storing Fastr Networks and (Dockerized) Tools.
Home-page: https://gitlab.com/radiology/infrastructure/resources/fastrpi/fastrpi
Author: A.G.J. Harms, H.C. Achterberg, A. Versteeg
Author-email: a.harms@erasmusmc.nl, h.achterberg@erasmusmc.nl, a.versteeg@erasmusmc.nl
License: Apache 2.0
Classifier: Development Status :: 4 - Beta
Classifier: Intended Audience :: Developers
Classifier: Intended Audience :: Science/Research
Classifier: Intended Audience :: Healthcare Industry
Classifier: Intended Audience :: Information Technology
Classifier: Intended Audience :: Education
Classifier: License :: OSI Approved :: Apache Software License
Classifier: Natural Language :: English
Classifier: Operating System :: OS Independent
Classifier: Programming Language :: Python :: 3.8
Classifier: Programming Language :: Python :: 3.9
Classifier: Programming Language :: Python :: 3.10
Classifier: Programming Language :: Python :: 3.11
Classifier: Programming Language :: Python :: 3 :: Only
Classifier: Topic :: Scientific/Engineering :: Information Analysis
Classifier: Topic :: System :: Distributed Computing
Classifier: Topic :: Utilities
License-File: LICENSE
Requires-Dist: Click
Requires-Dist: docker
Requires-Dist: fastr>=3.4.0
Requires-Dist: gitpython
Requires-Dist: schema
Requires-Dist: pyyaml
Requires-Dist: ruamel.yaml
Requires-Dist: tabulate
Requires-Dist: requests
Requires-Dist: questionary
